face_sdk222/__init__.py
face_sdk222/config/__init__.py
face_sdk222/core/__init__.py
face_sdk222/logs/__init__.py
face_sdk222/models/__init__.py
face_sdk222/sample_api/__init__.py
face_sdk222/sample_api/sample_face_pipline.py
face_sdk222/utils/BuzException.py
face_sdk222/utils/__init__.py
face_sdk222/utils/lms_trans.py
face_sdk222-0.0.5.dist-info/LICENSE
face_sdk222-0.0.5.dist-info/METADATA
face_sdk222-0.0.5.dist-info/WHEEL
face_sdk222-0.0.5.dist-info/top_level.txt
face_sdk222-0.0.5.dist-info/RECORD
